decay/__init__.py
decay/__version__.py
decay/constants.py
decay/decay.py
decay/host.py
decay/item.py
decay/kind.py
decay/registry.py
decay/decays/__init__.py
decay/decays/linear.py
decay/decays/no_decay.py
decay/decays/sample/__init__.py
decay/decays/sample/circle.py
decay/decays/sample/cube.py
decay/decays/sample/half_sudden.py
decay/decays/sample/inverse_circle.py
decay/decays/sample/inverse_parabola.py
decay/decays/sample/parabola.py
decay/decays/sample/sigmoid.py
decay/decays/sample/square_root.py
decay/decays/sample/sudden.py
decay/decays/sample/three_sine.py
decay-0.1.1.dist-info/LICENSE
decay-0.1.1.dist-info/METADATA
decay-0.1.1.dist-info/PKG-INFO.sync-conflict-20191206-181015-345KEVS
decay-0.1.1.dist-info/WHEEL
decay-0.1.1.dist-info/top_level.txt
decay-0.1.1.dist-info/RECORD
